[
  {
    "year": 1968,
    "ageMen": [
      614,
      557,
      502,
      503,
      703,
      604,
      448,
      381,
      424,
      533,
      504,
      459,
      406,
      315,
      235,
      149,
      97,
      42,
      11,
      2,
      0,
      0
    ],
    "ageWoman": [
      635,
      510,
      397,
      527,
      648,
      518,
      434,
      378,
      433,
      517,
      471,
      449,
      381,
      351,
      261,
      232,
      113,
      44,
      12,
      2,
      0,
      0
    ]
  },
  {
    "year": 1969,
    "ageMen": [
      572,
      566,
      503,
      495,
      638,
      619,
      501,
      372,
      398,
      536,
      501,
      479,
      390,
      339,
      240,
      148,
      93,
      36,
      10,
      2,
      0,
      0
    ],
    "ageWoman": [
      598,
      550,
      425,
      487,
      616,
      521,
      445,
      372,
      438,
      519,
      457,
      472,
      393,
      342,
      295,
      236,
      119,
      49,
      17,
      2,
      0,
      0
    ]
  },
  {
    "year": 1970,
    "ageMen": [
      595,
      566,
      523,
      465,
      625,
      662,
      525,
      379,
      397,
      489,
      503,
      490,
      390,
      361,
      246,
      155,
      90,
      39,
      11,
      1,
      0,
      0
    ],
    "ageWoman": [
      558,
      590,
      405,
      457,
      583,
      568,
      456,
      351,
      408,
      489,
      489,
      460,
      417,
      339,
      315,
      229,
      135,
      51,
      15,
      3,
      0,
      0
    ]
  },
  {
    "year": 1971,
    "ageMen": [
      582,
      586,
      508,
      481,
      593,
      660,
      549,
      404,
      377,
      462,
      526,
      480,
      403,
      380,
      239,
      172,
      86,
      41,
      13,
      1,
      0,
      0
    ],
    "ageWoman": [
      532,
      587,
      447,
      447,
      516,
      598,
      474,
      375,
      377,
      466,
      503,
      467,
      435,
      346,
      318,
      225,
      146,
      54,
      15,
      5,
      0,
      0
    ]
  },
  {
    "year": 1972,
    "ageMen": [
      552,
      580,
      513,
      492,
      553,
      640,
      562,
      398,
      392,
      422,
      517,
      497,
      410,
      367,
      264,
      171,
      88,
      41,
      15,
      0,
      0,
      0
    ],
    "ageWoman": [
      524,
      618,
      483,
      394,
      483,
      601,
      493,
      388,
      384,
      435,
      517,
      476,
      430,
      350,
      317,
      228,
      152,
      56,
      17,
      4,
      0,
      0
    ]
  },
  {
    "year": 1973,
    "ageMen": [
      551,
      589,
      531,
      495,
      478,
      640,
      576,
      431,
      365,
      409,
      514,
      490,
      448,
      362,
      261,
      172,
      89,
      45,
      13,
      0,
      0,
      0
    ],
    "ageWoman": [
      496,
      623,
      512,
      380,
      469,
      594,
      508,
      413,
      351,
      429,
      526,
      459,
      441,
      375,
      321,
      233,
      154,
      56,
      16,
      4,
      1,
      0
    ]
  },
  {
    "year": 1974,
    "ageMen": [
      557,
      586,
      537,
      497,
      462,
      582,
      589,
      481,
      356,
      389,
      506,
      469,
      444,
      364,
      281,
      185,
      87,
      42,
      10,
      2,
      0,
      0
    ],
    "ageWoman": [
      498,
      571,
      525,
      402,
      423,
      567,
      514,
      417,
      356,
      420,
      511,
      450,
      450,
      384,
      312,
      244,
      154,
      59,
      19,
      3,
      1,
      0
    ]
  },
  {
    "year": 1975,
    "ageMen": [
      533,
      565,
      562,
      513,
      452,
      556,
      601,
      505,
      362,
      397,
      468,
      478,
      451,
      353,
      307,
      178,
      93,
      37,
      12,
      0,
      0,
      0
    ],
    "ageWoman": [
      509,
      547,
      549,
      404,
      407,
      531,
      551,
      435,
      336,
      405,
      475,
      481,
      444,
      403,
      311,
      260,
      155,
      68,
      21,
      2,
      0,
      0
    ]
  },
  {
    "year": 1976,
    "ageMen": [
      492,
      551,
      578,
      498,
      468,
      536,
      602,
      521,
      391,
      375,
      439,
      484,
      429,
      371,
      317,
      170,
      107,
      38,
      11,
      1,
      0,
      0
    ],
    "ageWoman": [
      495,
      504,
      559,
      436,
      402,
      495,
      565,
      451,
      362,
      369,
      454,
      493,
      447,
      412,
      309,
      264,
      161,
      72,
      22,
      2,
      0,
      0
    ]
  },
  {
    "year": 1977,
    "ageMen": [
      463,
      537,
      579,
      512,
      507,
      515,
      609,
      529,
      390,
      391,
      407,
      482,
      446,
      369,
      312,
      187,
      107,
      43,
      15,
      1,
      0,
      0
    ],
    "ageWoman": [
      449,
      493,
      591,
      480,
      365,
      456,
      601,
      453,
      377,
      377,
      428,
      500,
      451,
      417,
      319,
      267,
      167,
      84,
      19,
      3,
      0,
      0
    ]
  },
  {
    "year": 1978,
    "ageMen": [
      474,
      509,
      583,
      542,
      504,
      497,
      623,
      551,
      418,
      368,
      390,
      494,
      444,
      389,
      317,
      187,
      109,
      41,
      14,
      1,
      0,
      0
    ],
    "ageWoman": [
      441,
      496,
      591,
      496,
      389,
      454,
      603,
      474,
      399,
      351,
      420,
      516,
      446,
      418,
      340,
      266,
      170,
      96,
      19,
      3,
      0,
      0
    ]
  },
  {
    "year": 1979,
    "ageMen": [
      438,
      525,
      567,
      548,
      503,
      488,
      597,
      574,
      463,
      370,
      377,
      493,
      442,
      393,
      307,
      205,
      110,
      41,
      19,
      1,
      0,
      0
    ],
    "ageWoman": [
      400,
      516,
      564,
      507,
      421,
      424,
      588,
      491,
      414,
      354,
      411,
      517,
      419,
      433,
      352,
      256,
      187,
      96,
      19,
      4,
      0,
      0
    ]
  },
  {
    "year": 1980,
    "ageMen": [
      432,
      526,
      559,
      570,
      527,
      479,
      584,
      600,
      499,
      364,
      390,
      450,
      435,
      417,
      298,
      224,
      107,
      46,
      19,
      2,
      0,
      0
    ],
    "ageWoman": [
      386,
      521,
      544,
      552,
      394,
      437,
      553,
      553,
      435,
      337,
      392,
      479,
      460,
      426,
      376,
      259,
      189,
      95,
      24,
      4,
      0,
      0
    ]
  },
  {
    "year": 1981,
    "ageMen": [
      428,
      508,
      554,
      584,
      502,
      454,
      553,
      601,
      514,
      396,
      363,
      425,
      449,
      394,
      314,
      235,
      105,
      50,
      13,
      3,
      1,
      0
    ],
    "ageWoman": [
      350,
      499,
      513,
      563,
      396,
      405,
      504,
      582,
      441,
      366,
      360,
      457,
      468,
      435,
      382,
      267,
      174,
      97,
      23,
      6,
      0,
      0
    ]
  },
  {
    "year": 1982,
    "ageMen": [
      418,
      482,
      542,
      566,
      521,
      464,
      533,
      621,
      514,
      404,
      386,
      386,
      439,
      399,
      307,
      232,
      118,
      44,
      10,
      5,
      1,
      0
    ],
    "ageWoman": [
      328,
      465,
      506,
      584,
      403,
      362,
      480,
      615,
      444,
      381,
      364,
      423,
      472,
      434,
      382,
      271,
      182,
      95,
      33,
      6,
      1,
      0
    ]
  },
  {
    "year": 1983,
    "ageMen": [
      411,
      483,
      504,
      569,
      519,
      479,
      483,
      618,
      535,
      432,
      373,
      369,
      459,
      399,
      326,
      230,
      109,
      49,
      10,
      4,
      0,
      0
    ],
    "ageWoman": [
      336,
      425,
      511,
      572,
      433,
      354,
      464,
      596,
      463,
      398,
      355,
      415,
      487,
      414,
      380,
      291,
      182,
      98,
      38,
      2,
      0,
      0
    ]
  },
  {
    "year": 1984,
    "ageMen": [
      427,
      448,
      521,
      552,
      519,
      462,
      472,
      575,
      553,
      475,
      357,
      357,
      450,
      389,
      336,
      219,
      125,
      42,
      11,
      4,
      0,
      0
    ],
    "ageWoman": [
      330,
      396,
      518,
      561,
      447,
      370,
      427,
      588,
      479,
      414,
      343,
      400,
      483,
      403,
      405,
      301,
      184,
      107,
      30,
      4,
      0,
      0
    ]
  },
  {
    "year": 1985,
    "ageMen": [
      417,
      416,
      530,
      529,
      557,
      475,
      447,
      556,
      588,
      480,
      362,
      374,
      420,
      376,
      356,
      222,
      131,
      41,
      11,
      4,
      0,
      0
    ],
    "ageWoman": [
      339,
      374,
      515,
      537,
      466,
      360,
      404,
      539,
      543,
      426,
      330,
      387,
      445,
      436,
      396,
      315,
      190,
      104,
      37,
      6,
      0,
      0
    ]
  },
  {
    "year": 1986,
    "ageMen": [
      395,
      414,
      516,
      529,
      561,
      478,
      431,
      532,
      600,
      489,
      389,
      360,
      396,
      400,
      334,
      238,
      145,
      50,
      11,
      3,
      0,
      0
    ],
    "ageWoman": [
      358,
      350,
      510,
      501,
      477,
      376,
      382,
      504,
      573,
      431,
      366,
      347,
      433,
      437,
      402,
      319,
      190,
      105,
      41,
      7,
      0,
      0
    ]
  },
  {
    "year": 1987,
    "ageMen": [
      418,
      413,
      484,
      514,
      561,
      477,
      440,
      511,
      610,
      496,
      390,
      378,
      366,
      405,
      339,
      241,
      142,
      65,
      10,
      1,
      0,
      0
    ],
    "ageWoman": [
      385,
      350,
      454,
      498,
      488,
      384,
      356,
      478,
      596,
      438,
      378,
      360,
      402,
      456,
      408,
      332,
      200,
      109,
      44,
      7,
      0,
      0
    ]
  },
  {
    "year": 1988,
    "ageMen": [
      413,
      410,
      490,
      496,
      595,
      480,
      460,
      479,
      597,
      518,
      414,
      360,
      349,
      409,
      352,
      247,
      148,
      54,
      12,
      2,
      0,
      0
    ],
    "ageWoman": [
      405,
      371,
      429,
      498,
      485,
      406,
      355,
      468,
      572,
      464,
      404,
      338,
      398,
      463,
      395,
      344,
      226,
      95,
      44,
      12,
      0,
      0
    ]
  },
  {
    "year": 1989,
    "ageMen": [
      435,
      431,
      454,
      522,
      561,
      523,
      466,
      448,
      572,
      554,
      458,
      342,
      345,
      408,
      345,
      255,
      141,
      64,
      13,
      1,
      1,
      0
    ],
    "ageWoman": [
      426,
      379,
      405,
      514,
      457,
      431,
      378,
      430,
      580,
      476,
      411,
      332,
      386,
      467,
      369,
      357,
      240,
      108,
      43,
      8,
      0,
      0
    ]
  },
  {
    "year": 1990,
    "ageMen": [
      444,
      433,
      431,
      538,
      521,
      552,
      484,
      420,
      567,
      580,
      464,
      346,
      357,
      390,
      334,
      269,
      140,
      74,
      13,
      2,
      1,
      0
    ],
    "ageWoman": [
      446,
      376,
      389,
      526,
      469,
      451,
      367,
      417,
      548,
      538,
      424,
      324,
      381,
      427,
      406,
      345,
      249,
      125,
      39,
      14,
      1,
      0
    ]
  },
  {
    "year": 1991,
    "ageMen": [
      448,
      415,
      438,
      519,
      519,
      550,
      500,
      428,
      541,
      596,
      478,
      366,
      340,
      363,
      343,
      250,
      159,
      73,
      15,
      1,
      0,
      0
    ],
    "ageWoman": [
      462,
      397,
      379,
      511,
      440,
      472,
      392,
      400,
      497,
      591,
      418,
      356,
      346,
      418,
      407,
      351,
      241,
      132,
      40,
      13,
      0,
      0
    ]
  },
  {
    "year": 1992,
    "ageMen": [
      456,
      429,
      435,
      483,
      503,
      552,
      503,
      436,
      510,
      598,
      493,
      370,
      352,
      338,
      345,
      255,
      155,
      73,
      21,
      1,
      0,
      0
    ],
    "ageWoman": [
      471,
      414,
      372,
      454,
      445,
      489,
      410,
      373,
      468,
      606,
      429,
      371,
      349,
      395,
      418,
      353,
      238,
      136,
      41,
      12,
      0,
      0
    ]
  },
  {
    "year": 1993,
    "ageMen": [
      480,
      431,
      423,
      484,
      476,
      547,
      520,
      448,
      484,
      579,
      519,
      393,
      334,
      327,
      340,
      267,
      161,
      71,
      18,
      2,
      0,
      0
    ],
    "ageWoman": [
      483,
      434,
      379,
      429,
      437,
      476,
      438,
      376,
      450,
      589,
      460,
      390,
      338,
      387,
      422,
      342,
      240,
      140,
      45,
      12,
      1,
      0
    ]
  },
  {
    "year": 1994,
    "ageMen": [
      486,
      461,
      434,
      458,
      481,
      536,
      530,
      460,
      449,
      554,
      557,
      438,
      317,
      315,
      354,
      270,
      157,
      72,
      20,
      3,
      0,
      0
    ],
    "ageWoman": [
      477,
      455,
      383,
      414,
      436,
      461,
      451,
      393,
      422,
      585,
      487,
      398,
      338,
      379,
      418,
      328,
      261,
      144,
      55,
      8,
      1,
      0
    ]
  },
  {
    "year": 1995,
    "ageMen": [
      473,
      463,
      428,
      443,
      438,
      508,
      545,
      472,
      408,
      552,
      571,
      452,
      329,
      322,
      337,
      266,
      170,
      68,
      21,
      3,
      0,
      0
    ],
    "ageWoman": [
      457,
      460,
      378,
      402,
      446,
      442,
      475,
      372,
      418,
      539,
      540,
      418,
      328,
      368,
      390,
      363,
      257,
      166,
      59,
      7,
      0,
      0
    ]
  },
  {
    "year": 1996,
    "ageMen": [
      443,
      464,
      422,
      453,
      405,
      464,
      539,
      470,
      414,
      533,
      574,
      466,
      350,
      315,
      313,
      263,
      173,
      74,
      22,
      4,
      0,
      0
    ],
    "ageWoman": [
      425,
      478,
      392,
      373,
      405,
      411,
      465,
      398,
      394,
      492,
      588,
      421,
      350,
      334,
      379,
      366,
      263,
      161,
      62,
      7,
      1,
      0
    ]
  },
  {
    "year": 1997,
    "ageMen": [
      413,
      477,
      435,
      442,
      356,
      442,
      523,
      470,
      424,
      506,
      569,
      469,
      353,
      329,
      288,
      256,
      180,
      74,
      19,
      5,
      0,
      0
    ],
    "ageWoman": [
      401,
      477,
      409,
      358,
      347,
      392,
      481,
      405,
      360,
      470,
      596,
      428,
      370,
      338,
      370,
      371,
      275,
      153,
      60,
      11,
      3,
      0
    ]
  },
  {
    "year": 1998,
    "ageMen": [
      382,
      493,
      443,
      433,
      382,
      401,
      510,
      478,
      427,
      479,
      556,
      496,
      378,
      317,
      288,
      270,
      178,
      80,
      23,
      2,
      1,
      0
    ],
    "ageWoman": [
      375,
      479,
      424,
      365,
      337,
      372,
      463,
      435,
      365,
      443,
      574,
      447,
      397,
      328,
      364,
      379,
      276,
      139,
      78,
      10,
      3,
      0
    ]
  },
  {
    "year": 1999,
    "ageMen": [
      371,
      481,
      457,
      439,
      368,
      395,
      495,
      489,
      438,
      437,
      535,
      525,
      418,
      300,
      274,
      284,
      180,
      83,
      22,
      3,
      0,
      0
    ],
    "ageWoman": [
      351,
      461,
      451,
      357,
      345,
      358,
      451,
      448,
      386,
      416,
      569,
      475,
      391,
      331,
      355,
      374,
      278,
      161,
      66,
      16,
      2,
      0
    ]
  },
  {
    "year": 2000,
    "ageMen": [
      344,
      463,
      479,
      430,
      343,
      370,
      458,
      507,
      446,
      392,
      537,
      537,
      437,
      309,
      287,
      276,
      174,
      97,
      23,
      3,
      0,
      0
    ],
    "ageWoman": [
      366,
      443,
      453,
      360,
      291,
      376,
      412,
      474,
      362,
      410,
      527,
      527,
      403,
      315,
      345,
      342,
      298,
      168,
      68,
      16,
      2,
      0
    ]
  },
  {
    "year": 2001,
    "ageMen": [
      337,
      425,
      468,
      437,
      347,
      325,
      445,
      505,
      441,
      391,
      506,
      552,
      447,
      337,
      286,
      257,
      173,
      96,
      27,
      4,
      1,
      0
    ],
    "ageWoman": [
      350,
      412,
      455,
      371,
      272,
      348,
      381,
      463,
      378,
      384,
      485,
      566,
      404,
      332,
      315,
      331,
      304,
      178,
      62,
      16,
      2,
      0
    ]
  },
  {
    "year": 2002,
    "ageMen": [
      331,
      402,
      471,
      457,
      322,
      312,
      422,
      491,
      460,
      405,
      482,
      552,
      459,
      342,
      302,
      242,
      171,
      105,
      24,
      6,
      1,
      0
    ],
    "ageWoman": [
      372,
      387,
      474,
      385,
      270,
      325,
      365,
      486,
      392,
      370,
      450,
      581,
      415,
      356,
      310,
      321,
      306,
      177,
      58,
      14,
      1,
      0
    ]
  },
  {
    "year": 2003,
    "ageMen": [
      334,
      380,
      492,
      447,
      320,
      306,
      377,
      497,
      469,
      404,
      459,
      538,
      486,
      364,
      293,
      246,
      189,
      100,
      30,
      4,
      1,
      0
    ],
    "ageWoman": [
      360,
      370,
      458,
      406,
      282,
      312,
      355,
      470,
      417,
      373,
      424,
      566,
      444,
      364,
      308,
      316,
      308,
      165,
      57,
      22,
      1,
      0
    ]
  },
  {
    "year": 2004,
    "ageMen": [
      338,
      369,
      471,
      454,
      320,
      307,
      375,
      475,
      481,
      417,
      410,
      517,
      497,
      407,
      276,
      238,
      204,
      100,
      32,
      2,
      1,
      0
    ],
    "ageWoman": [
      343,
      351,
      448,
      420,
      262,
      297,
      353,
      449,
      445,
      381,
      399,
      559,
      469,
      369,
      300,
      321,
      294,
      166,
      72,
      15,
      2,
      0
    ]
  },
  {
    "year": 2005,
    "ageMen": [
      340,
      351,
      452,
      466,
      334,
      306,
      358,
      444,
      496,
      438,
      381,
      515,
      515,
      413,
      283,
      234,
      194,
      98,
      28,
      3,
      0,
      0
    ],
    "ageWoman": [
      317,
      364,
      435,
      441,
      284,
      278,
      365,
      420,
      475,
      365,
      416,
      518,
      516,
      389,
      284,
      309,
      273,
      193,
      71,
      17,
      1,
      0
    ]
  },
  {
    "year": 2006,
    "ageMen": [
      340,
      340,
      446,
      459,
      365,
      289,
      337,
      435,
      496,
      444,
      388,
      494,
      532,
      426,
      310,
      241,
      185,
      96,
      31,
      5,
      0,
      0
    ],
    "ageWoman": [
      315,
      359,
      414,
      450,
      305,
      264,
      355,
      395,
      482,
      394,
      400,
      479,
      560,
      406,
      303,
      276,
      282,
      204,
      72,
      16,
      1,
      0
    ]
  },
  {
    "year": 2007,
    "ageMen": [
      343,
      335,
      413,
      477,
      390,
      287,
      318,
      423,
      495,
      458,
      408,
      467,
      535,
      445,
      299,
      256,
      179,
      93,
      37,
      3,
      0,
      0
    ],
    "ageWoman": [
      288,
      376,
      396,
      450,
      308,
      266,
      328,
      377,
      492,
      409,
      392,
      441,
      585,
      416,
      324,
      278,
      272,
      220,
      72,
      16,
      2,
      0
    ]
  },
  {
    "year": 2008,
    "ageMen": [
      352,
      342,
      396,
      487,
      378,
      296,
      317,
      378,
      493,
      471,
      409,
      446,
      525,
      461,
      318,
      249,
      176,
      110,
      31,
      1,
      0,
      0
    ],
    "ageWoman": [
      267,
      375,
      385,
      448,
      324,
      264,
      327,
      374,
      475,
      415,
      392,
      426,
      570,
      447,
      337,
      282,
      258,
      213,
      73,
      9,
      4,
      0
    ]
  },
  {
    "year": 2009,
    "ageMen": [
      339,
      362,
      390,
      476,
      388,
      295,
      310,
      383,
      481,
      473,
      424,
      419,
      504,
      476,
      367,
      240,
      170,
      115,
      32,
      3,
      0,
      0
    ],
    "ageWoman": [
      280,
      351,
      372,
      447,
      354,
      260,
      307,
      384,
      459,
      442,
      393,
      396,
      558,
      472,
      349,
      274,
      257,
      197,
      84,
      17,
      2,
      0
    ]
  },
  {
    "year": 2010,
    "ageMen": [
      327,
      361,
      366,
      464,
      386,
      304,
      305,
      388,
      447,
      488,
      445,
      382,
      509,
      490,
      389,
      243,
      182,
      112,
      30,
      1,
      0,
      0
    ],
    "ageWoman": [
      282,
      343,
      378,
      442,
      368,
      274,
      280,
      402,
      429,
      468,
      370,
      405,
      520,
      525,
      359,
      270,
      245,
      183,
      98,
      23,
      2,
      0
    ]
  },
  {
    "year": 2011,
    "ageMen": [
      328,
      358,
      355,
      461,
      393,
      315,
      316,
      356,
      440,
      494,
      453,
      386,
      484,
      518,
      395,
      263,
      177,
      104,
      28,
      1,
      0,
      0
    ],
    "ageWoman": [
      283,
      341,
      374,
      427,
      383,
      288,
      286,
      387,
      406,
      473,
      396,
      396,
      470,
      565,
      389,
      278,
      229,
      178,
      106,
      19,
      3,
      0
    ]
  },
  {
    "year": 2012,
    "ageMen": [
      341,
      360,
      346,
      433,
      427,
      345,
      313,
      345,
      441,
      488,
      466,
      399,
      457,
      530,
      403,
      254,
      184,
      102,
      33,
      3,
      0,
      0
    ],
    "ageWoman": [
      303,
      296,
      399,
      411,
      422,
      277,
      300,
      349,
      397,
      494,
      417,
      383,
      440,
      588,
      393,
      285,
      236,
      168,
      107,
      16,
      2,
      0
    ]
  },
  {
    "year": 2013,
    "ageMen": [
      338,
      366,
      370,
      409,
      457,
      356,
      316,
      359,
      402,
      496,
      476,
      414,
      446,
      513,
      427,
      266,
      186,
      105,
      42,
      4,
      0,
      0
    ],
    "ageWoman": [
      317,
      280,
      408,
      411,
      416,
      328,
      292,
      357,
      388,
      482,
      436,
      387,
      430,
      571,
      420,
      304,
      235,
      165,
      101,
      15,
      2,
      0
    ]
  },
  {
    "year": 2014,
    "ageMen": [
      363,
      344,
      372,
      397,
      467,
      399,
      344,
      346,
      401,
      488,
      473,
      434,
      404,
      510,
      441,
      314,
      180,
      108,
      47,
      4,
      0,
      0
    ],
    "ageWoman": [
      341,
      298,
      377,
      391,
      442,
      351,
      304,
      328,
      395,
      461,
      459,
      399,
      401,
      571,
      455,
      318,
      227,
      159,
      90,
      25,
      3,
      0
    ]
  },
  {
    "year": 2015,
    "ageMen": [
      378,
      381,
      392,
      405,
      463,
      432,
      363,
      350,
      404,
      467,
      495,
      453,
      379,
      500,
      456,
      343,
      179,
      124,
      39,
      4,
      0,
      0
    ],
    "ageWoman": [
      342,
      318,
      370,
      400,
      427,
      368,
      323,
      318,
      411,
      447,
      491,
      372,
      423,
      520,
      503,
      329,
      224,
      149,
      86,
      26,
      4,
      0
    ]
  },
  {
    "year": 2016,
    "ageMen": [
      369,
      382,
      394,
      407,
      447,
      441,
      367,
      360,
      372,
      466,
      503,
      465,
      402,
      466,
      479,
      352,
      198,
      117,
      40,
      6,
      0,
      0
    ],
    "ageWoman": [
      359,
      325,
      360,
      394,
      392,
      391,
      333,
      322,
      407,
      432,
      492,
      405,
      409,
      475,
      535,
      357,
      221,
      143,
      84,
      31,
      3,
      0
    ]
  },
  {
    "year": 2017,
    "ageMen": [
      370,
      385,
      404,
      400,
      418,
      464,
      385,
      349,
      363,
      457,
      495,
      471,
      423,
      446,
      488,
      358,
      193,
      117,
      43,
      9,
      1,
      0
    ],
    "ageWoman": [
      378,
      336,
      326,
      421,
      389,
      396,
      329,
      332,
      371,
      410,
      510,
      429,
      386,
      447,
      555,
      366,
      244,
      152,
      80,
      34,
      4,
      0
    ]
  },
  {
    "year": 2018,
    "ageMen": [
      379,
      382,
      408,
      428,
      414,
      488,
      389,
      371,
      360,
      418,
      508,
      485,
      430,
      440,
      484,
      379,
      215,
      113,
      47,
      7,
      1,
      0
    ],
    "ageWoman": [
      381,
      361,
      322,
      436,
      360,
      402,
      362,
      348,
      376,
      405,
      492,
      456,
      392,
      437,
      542,
      390,
      266,
      154,
      81,
      26,
      3,
      0
    ]
  },
  {
    "year": 2019,
    "ageMen": [
      377,
      391,
      387,
      421,
      404,
      466,
      413,
      346,
      349,
      415,
      510,
      495,
      440,
      416,
      479,
      384,
      252,
      109,
      55,
      5,
      0,
      0
    ],
    "ageWoman": [
      376,
      362,
      330,
      414,
      321,
      414,
      379,
      344,
      339,
      424,
      467,
      465,
      415,
      407,
      540,
      419,
      278,
      159,
      93,
      25,
      2,
      0
    ]
  },
  {
    "year": 2020,
    "ageMen": [
      373,
      375,
      412,
      405,
      381,
      438,
      457,
      355,
      343,
      417,
      465,
      514,
      446,
      386,
      479,
      405,
      272,
      103,
      59,
      9,
      0,
      0
    ],
    "ageWoman": [
      364,
      365,
      328,
      396,
      316,
      388,
      408,
      340,
      324,
      429,
      445,
      493,
      381,
      427,
      501,
      474,
      279,
      166,
      84,
      35,
      2,
      0
    ]
  },
  {
    "year": 2021,
    "ageMen": [
      384,
      387,
      414,
      419,
      381,
      409,
      477,
      381,
      361,
      379,
      459,
      508,
      461,
      389,
      457,
      429,
      276,
      113,
      51,
      13,
      1,
      0
    ],
    "ageWoman": [
      352,
      392,
      326,
      382,
      304,
      358,
      429,
      350,
      346,
      409,
      429,
      499,
      414,
      412,
      455,
      509,
      298,
      170,
      77,
      34,
      6,
      0
    ]
  },
  {
    "year": 2022,
    "ageMen": [
      370,
      390,
      408,
      425,
      362,
      403,
      466,
      402,
      371,
      362,
      457,
      504,
      463,
      412,
      431,
      437,
      295,
      120,
      51,
      10,
      1,
      0
    ],
    "ageWoman": [
      329,
      392,
      344,
      342,
      320,
      334,
      457,
      346,
      358,
      387,
      420,
      499,
      445,
      386,
      433,
      527,
      306,
      191,
      93,
      29,
      5,
      0
    ]
  }
]